flask_dbpacemaker/__init__.py
flask_dbpacemaker/db_pacemaker.py
Flask_DBPacemaker-1.2.5.dist-info/LICENSE
Flask_DBPacemaker-1.2.5.dist-info/METADATA
Flask_DBPacemaker-1.2.5.dist-info/WHEEL
Flask_DBPacemaker-1.2.5.dist-info/top_level.txt
Flask_DBPacemaker-1.2.5.dist-info/RECORD
