Metadata-Version: 2.1
Name: Flask-DBPacemaker
Version: 1.2.5
Summary: Hook db connection when you're running a long term sleep crawler assignment.
Home-page: https://github.com/Ron-Chang/flask_dbpacemaker
Author: Ron Chang
Author-email: ron.hsien.chang@gmail.com
License: MIT
Platform: UNKNOWN
Requires-Python: >=3.6
Requires-Dist: SQLAlchemy (>=1.2.10)
Requires-Dist: Flask (>=1.0.2)
Requires-Dist: Flask-APScheduler (>=1.11.0)
Requires-Dist: Flask-SQLAlchemy (>=2.3.2)
